kraken_extract_from_text/__init__.py
kraken_extract_from_text/kraken_extract_from_text.py
kraken_extract_from_text/extractors/__init__.py
kraken_extract_from_text/extractors/extract_emails.py
kraken_extract_from_text/extractors/extract_ioc.py
kraken_extract_from_text/extractors/extract_urls.py
kraken_text_analysis-0.0.4.dist-info/LICENSE.txt
kraken_text_analysis-0.0.4.dist-info/METADATA
kraken_text_analysis-0.0.4.dist-info/WHEEL
kraken_text_analysis-0.0.4.dist-info/top_level.txt
kraken_text_analysis-0.0.4.dist-info/RECORD
